class_email/__init__.py
class_email-0.1.1.dist-info/METADATA
class_email-0.1.1.dist-info/WHEEL
class_email-0.1.1.dist-info/entry_points.txt
class_email-0.1.1.dist-info/licenses/LICENSE
class_email-0.1.1.dist-info/RECORD
