Metadata-Version: 2.4
Name: class-email
Version: 0.1.1
Summary: A tool to output .eml files for opening in your email client and (optionally) sending them with SMTP.
Project-URL: Repository, https://github.com/HamishWHC/class-email.git
Project-URL: Issues, https://github.com/HamishWHC/class-email/issues
Author-email: Hamish Cox <hamish@hamishwhc.com>
Maintainer-email: Hamish Cox <hamish@hamishwhc.com>
License: Copyright © 2024 Hamish Cox
License-File: LICENSE
Classifier: Development Status :: 4 - Beta
Classifier: Environment :: Console
Classifier: Intended Audience :: Education
Classifier: Intended Audience :: End Users/Desktop
Classifier: License :: OSI Approved :: MIT License
Classifier: Operating System :: MacOS
Classifier: Operating System :: Microsoft :: Windows
Classifier: Operating System :: POSIX :: Linux
Classifier: Programming Language :: Python :: 3
Classifier: Programming Language :: Python :: 3 :: Only
Classifier: Programming Language :: Python :: 3.9
Classifier: Programming Language :: Python :: 3.10
Classifier: Programming Language :: Python :: 3.11
Classifier: Programming Language :: Python :: 3.12
Classifier: Programming Language :: Python :: 3.13
Classifier: Topic :: Communications :: Email
Classifier: Topic :: Text Processing :: Markup :: HTML
Classifier: Topic :: Utilities
Requires-Python: >=3.9
Requires-Dist: click>=8.1.7
Requires-Dist: jinja2>=3.1.4
Requires-Dist: tqdm>=4.67.1
